knmi_weather_mcp/__init__.py
knmi_weather_mcp/location.py
knmi_weather_mcp/models.py
knmi_weather_mcp/server.py
knmi_weather_mcp/station.py
knmi_weather_mcp/weather.py
knmi_weather_mcp-0.1.0.dist-info/METADATA
knmi_weather_mcp-0.1.0.dist-info/WHEEL
knmi_weather_mcp-0.1.0.dist-info/licenses/LICENSE
knmi_weather_mcp-0.1.0.dist-info/RECORD
